archguide_mcp/__init__.py
archguide_mcp/__main__.py
archguide_mcp/server.py
archguide_mcp-1.0.0.dist-info/licenses/LICENSE
archguide_mcp-1.0.0.dist-info/METADATA
archguide_mcp-1.0.0.dist-info/WHEEL
archguide_mcp-1.0.0.dist-info/entry_points.txt
archguide_mcp-1.0.0.dist-info/top_level.txt
archguide_mcp-1.0.0.dist-info/RECORD
