Metadata-Version: 2.4
Name: archguide-mcp
Version: 1.0.0
Summary: Architecture Guidelines MCP Server
Author-email: Ioan Salau <ioan.salau@gmail.com>
License: MIT
Project-URL: Homepage, https://github.com/yourusername/archguide-mcp
Project-URL: Repository, https://github.com/yourusername/archguide-mcp
Project-URL: Bug Tracker, https://github.com/yourusername/archguide-mcp/issues
Classifier: Development Status :: 4 - Beta
Classifier: Intended Audience :: Developers
Classifier: License :: OSI Approved :: MIT License
Classifier: Programming Language :: Python :: 3
Classifier: Programming Language :: Python :: 3.8
Classifier: Programming Language :: Python :: 3.9
Classifier: Programming Language :: Python :: 3.10
Classifier: Programming Language :: Python :: 3.11
Classifier: Programming Language :: Python :: 3.12
Requires-Python: >=3.8
License-File: LICENSE
Requires-Dist: mcp>=0.1.0
Requires-Dist: pydantic>=2.0
Requires-Dist: aiofiles>=23.0
Requires-Dist: pyyaml>=6.0
Dynamic: license-file
